hello_guys_dinh_sm.py
hello_guys_dinh_sm-0.0.2.dist-info/LICENSE
hello_guys_dinh_sm-0.0.2.dist-info/METADATA
hello_guys_dinh_sm-0.0.2.dist-info/WHEEL
hello_guys_dinh_sm-0.0.2.dist-info/top_level.txt
hello_guys_dinh_sm-0.0.2.dist-info/RECORD
